{
  "tabPane": [
    {
      "title": "SmartDashboard",
      "autoPopulate": true,
      "autoPopulatePrefix": "SmartDashboard/",
      "widgetPane": {
        "gridSize": 128.0,
        "showGrid": true,
        "hgap": 16.0,
        "vgap": 16.0,
        "titleType": 0,
        "tiles": {
          "0,0": {
            "size": [
              5,
              3
            ],
            "content": {
              "_type": "Field",
              "_source0": "network_table:///SmartDashboard/Field",
              "_title": "Field",
              "_glyph": 148,
              "_showGlyph": false,
              "Game/Game": "A2023_Charged_Up",
              "Visuals/Robot Icon Size": 50.0,
              "Visuals/Show Outside Circles": false,
              "Colors/trajectory": "#FFFFFFFF"
            }
          },
          "5,2": {
            "size": [
              2,
              2
            ],
            "content": {
              "_type": "Gyro",
              "_source0": "network_table:///SmartDashboard/Turret Angle",
              "_title": "Turret Angle",
              "_glyph": 148,
              "_showGlyph": false,
              "Visuals/Major tick spacing": 45.0,
              "Visuals/Starting angle": 180.0,
              "Visuals/Show tick mark ring": true,
              "Visuals/Counter clockwise": false
            }
          },
          "5,0": {
            "size": [
              2,
              2
            ],
            "content": {
              "_type": "Gyro",
              "_source0": "network_table:///SmartDashboard/Yaw",
              "_title": "Yaw",
              "_glyph": 148,
              "_showGlyph": false,
              "Visuals/Major tick spacing": 45.0,
              "Visuals/Starting angle": 180.0,
              "Visuals/Show tick mark ring": true,
              "Visuals/Counter clockwise": false
            }
          },
          "7,3": {
            "size": [
              2,
              1
            ],
            "content": {
              "_type": "Boolean Box",
              "_source0": "network_table:///SmartDashboard/Boost",
              "_title": "Boost",
              "_glyph": 148,
              "_showGlyph": false,
              "Colors/Color when true": "#7CFC00FF",
              "Colors/Color when false": "#8B0000FF"
            }
          },
          "7,0": {
            "size": [
              1,
              2
            ],
            "content": {
              "_type": "Number Bar",
              "_source0": "network_table:///SmartDashboard/Left Velocity",
              "_title": "Left Velocity",
              "_glyph": 148,
              "_showGlyph": false,
              "Range/Min": -4.0,
              "Range/Max": 4.0,
              "Range/Center": 0.0,
              "Visuals/Num tick marks": 9,
              "Visuals/Show text": true,
              "Visuals/Orientation": "VERTICAL"
            }
          },
          "8,0": {
            "size": [
              1,
              2
            ],
            "content": {
              "_type": "Number Bar",
              "_source0": "network_table:///SmartDashboard/Right Velocity",
              "_title": "Right Velocity",
              "_glyph": 148,
              "_showGlyph": false,
              "Range/Min": -4.0,
              "Range/Max": 4.0,
              "Range/Center": 0.0,
              "Visuals/Num tick marks": 9,
              "Visuals/Show text": true,
              "Visuals/Orientation": "VERTICAL"
            }
          },
          "7,2": {
            "size": [
              1,
              1
            ],
            "content": {
              "_type": "Text View",
              "_source0": "network_table:///SmartDashboard/Left Tick Vel",
              "_title": "Left Tick Vel",
              "_glyph": 148,
              "_showGlyph": false
            }
          },
          "8,2": {
            "size": [
              1,
              1
            ],
            "content": {
              "_type": "Text View",
              "_source0": "network_table:///SmartDashboard/Right Tick Vel",
              "_title": "Right Tick Vel",
              "_glyph": 148,
              "_showGlyph": false
            }
          }
        }
      }
    },
    {
      "title": "LiveWindow",
      "autoPopulate": true,
      "autoPopulatePrefix": "LiveWindow/",
      "widgetPane": {
        "gridSize": 128.0,
        "showGrid": true,
        "hgap": 16.0,
        "vgap": 16.0,
        "titleType": 0,
        "tiles": {}
      }
    }
  ],
  "windowGeometry": {
    "x": -7.199999809265137,
    "y": -7.199999809265137,
    "width": 1550.4000244140625,
    "height": 830.4000244140625
  }
}